dataIO/__init__.py
dataIO/any_is_none.py
dataIO/arrays.py
dataIO/beep.py
dataIO/congrid.py
dataIO/debug.py
dataIO/dicts.py
dataIO/files.py
dataIO/fn_add_subfix.py
dataIO/functions.py
dataIO/jpgToFits.py
dataIO/logger.py
dataIO/logs.py
dataIO/outliers.py
dataIO/read_blocks (1).py
dataIO/read_blocks(2).py
dataIO/read_blocks.py
dataIO/read_pars_from_namelist.py
dataIO/rebin.py
dataIO/roi.py
dataIO/running_mean.py
dataIO/span.py
dataIO/superlist.py
dataIO/test_span.py
dataIO/config/__init__.py
dataIO/config/extractConfigFromNB.py
dataIO/config/interface.py
dataIO/config/make_config.py
plotting/FastImshow.py
plotting/__init__.py
plotting/add_clickable_markers.py
plotting/add_mask.py
plotting/backends.py
plotting/captions.py
plotting/fignumber.py
plotting/imageCaption.py
plotting/imageKey.py
plotting/imageKey_v1.py
plotting/keyInterface.py
plotting/linestyles.py
plotting/multiplots.py
plotting/plot_labels.py
plotting/plot_positions.py
plotting/scale.py
plotting/test_interactive.py
plotting/test_rezoom.py
plotting/updating_plot.py
plotting/viewlims.py
plotting/xadd_clickable_markers.py
pyGEO3D/__init__.py
pyGEO3D/fit_3D_line.py
pyGEO3D/fit_3D_plane.py
pyGEO3D/geoShell.py
pyGEO3D/intersect_plane_line.py
pyGEO3D/ostruzione.py
pyProfile/__init__.py
pyProfile/makenicePSDplots.py
pyProfile/power_law.py
pyProfile/profile.py
pyProfile/profile_class.py
pyProfile/profile_v1.py
pyProfile/psd.py
pySurf/FEA.py
pySurf/PointCloud.py
pySurf/__init__.py
pySurf/_instrument_reader.py
pySurf/affine2D.py
pySurf/clip.py
pySurf/data2D.py
pySurf/data2D_class.py
pySurf/distanceTable.py
pySurf/find_internal_rectangle.py
pySurf/fit_cylinder.py
pySurf/instrumentReader.py
pySurf/outliers2d.py
pySurf/plane_fit.py
pySurf/points.py
pySurf/psd2d.py
pySurf/radial.py
pySurf/roi.py
pySurf/stress_compensation.py
pySurf/testSurfaces.py
pySurf/readers/__init__.py
pySurf/readers/cmmconvert.py
pySurf/readers/format_reader.py
pySurf/readers/instrumentReader.py
pySurf/readers/nid_reader.py
pyXsurf-1.6.1.dist-info/METADATA
pyXsurf-1.6.1.dist-info/WHEEL
pyXsurf-1.6.1.dist-info/top_level.txt
pyXsurf-1.6.1.dist-info/RECORD
